color_matcher/__init__.py
color_matcher/baseclass.py
color_matcher/hist_matcher.py
color_matcher/io_handler.py
color_matcher/mvgd_matcher.py
color_matcher/normalizer.py
color_matcher/reinhard_matcher.py
color_matcher/top_level.py
color_matcher/bin/cli.py
color_matcher-0.6.0.data/data/tests/data/scotland_house.png
color_matcher-0.6.0.data/data/tests/data/scotland_pitie.png
color_matcher-0.6.0.data/data/tests/data/scotland_plain.png
color_matcher-0.6.0.data/scripts/cli.py
tests/__init__.py
tests/frames.py
tests/img_downloader.py
tests/kodak_data_test.py
tests/unit_test.py
tests/data/scotland_house.png
tests/data/scotland_pitie.png
tests/data/scotland_plain.png
color_matcher-0.6.0.dist-info/LICENSE
color_matcher-0.6.0.dist-info/METADATA
color_matcher-0.6.0.dist-info/WHEEL
color_matcher-0.6.0.dist-info/entry_points.txt
color_matcher-0.6.0.dist-info/top_level.txt
color_matcher-0.6.0.dist-info/RECORD
