Metadata-Version: 2.1
Name: color-matcher
Version: 0.6.0
Summary: Package enabling color transfer across images
Home-page: http://github.com/hahnec/color-matcher
Author: Christopher Hahne
Author-email: inbox@christopherhahne.de
License: GNU GPL V3.0
Keywords: color match histogram matching image colour transfer monge kantorovich mkl pitie reinhardrecolor re-color recolour re-colour paintings film movie sequence automatic grading color-grading colour-grading equalize equalise equalization equalisation light-field lightfield stop-motion stopmotion
Requires-Python: >=3
License-File: LICENSE
Requires-Dist: ddt
Requires-Dist: docutils
Requires-Dist: imageio
Requires-Dist: matplotlib
Requires-Dist: numpy >=1.21
Requires-Dist: packaging >=24.2
